HCGB/__init__.py
HCGB/config/__init__.py
HCGB/config/extern_progs.py
HCGB/config/python_requirements.txt
HCGB/config/set_config.py
HCGB/config/setup_module.py
HCGB/format_conversion/__init__.py
HCGB/format_conversion/file_splitter.py
HCGB/format_conversion/gtf2bed.py
HCGB/functions/__init__.py
HCGB/functions/aesthetics_functions.py
HCGB/functions/blast_functions.py
HCGB/functions/fasta_functions.py
HCGB/functions/files_functions.py
HCGB/functions/info_functions.py
HCGB/functions/main_functions.py
HCGB/functions/math_functions.py
HCGB/functions/system_call_functions.py
HCGB/functions/time_functions.py
HCGB/sampleParser/__init__.py
HCGB/sampleParser/files.py
HCGB/sampleParser/merge.py
HCGB/sampleParser/samples.py
HCGB-0.6.2.dist-info/METADATA
HCGB-0.6.2.dist-info/WHEEL
HCGB-0.6.2.dist-info/top_level.txt
HCGB-0.6.2.dist-info/RECORD
