Metadata-Version: 2.1
Name: HCGB
Version: 0.6.2
Summary: Useful python functions
Home-page: https://github.com/HCGB-IGTP/HCGB_python_functions/
Author: Jose F. Sanchez-Herrero
Author-email: jfbioinformatics@gmail.com
License: MIT License
Classifier: Programming Language :: Python :: 3
Classifier: License :: OSI Approved :: MIT License
Classifier: Operating System :: OS Independent
Requires-Dist: biopython
Requires-Dist: pandas
Requires-Dist: patool
Requires-Dist: termcolor
Requires-Dist: wget
Requires-Dist: xlsxwriter
